meetbharodiya/__init__.py
meetbharodiya/swap_num.py
meetbharodiya-0.1.0.dist-info/METADATA
meetbharodiya-0.1.0.dist-info/WHEEL
meetbharodiya-0.1.0.dist-info/RECORD
