Metadata-Version: 2.1
Name: meetbharodiya
Version: 0.1.0
Summary: 
Author: meet.bharodiya
Author-email: meet.bharodiya@crestdatasys.com
Requires-Python: >=3.11,<4.0
Classifier: Programming Language :: Python :: 3
Classifier: Programming Language :: Python :: 3.11
Classifier: Programming Language :: Python :: 3.12
Requires-Dist: requests (>=2.31.0,<3.0.0)
